{"title":"动态SQL","uid":"83f1863d7d241c1d5ddb943bddf231fd","slug":"dynamicSQL","date":"2021-05-01T23:43:13.000Z","updated":"2021-05-01T23:44:31.701Z","comments":true,"path":"api/articles/dynamicSQL.json","keywords":null,"cover":null,"content":"<h4 id=\"动态sql语句\"><a href=\"#动态sql语句\" class=\"headerlink\" title=\"动态sql语句\"></a>动态sql语句</h4><p>**动态sql语句概述 **</p>\n<blockquote><span class=\"custom-blockquote-svg\"><svg width=\"24\" height=\"24\" viewBox=\"0 0 24 24\" fill=\"\" xmlns=\"http://www.w3.org/2000/svg\" data-reactroot=\"\">\n<path fill=\"\" d=\"M22 12C22 6.5 17.5 2 12 2C6.5 2 2 6.5 2 12C2 17.5 6.5 22 12 22C13.8 22 15.5 21.5 17 20.6L22 22L20.7 17C21.5 15.5 22 13.8 22 12Z\" undefined=\"1\"></path>\n<path fill=\"\" d=\"M15.97 11.5H16.04C17.12 11.5 18 12.38 18 13.47V13.53C18 14.62 17.12 15.5 16.03 15.5H15.96C14.88 15.5 14 14.62 14 13.53V13.46C14 12.38 14.88 11.5 15.97 11.5Z\" undefined=\"1\"></path>\n<path fill=\"\" d=\"M7.97 11.5H8.04C9.12 11.5 10 12.38 10 13.47V13.53C10 14.62 9.12 15.5 8.03 15.5H7.97C6.88 15.5 6 14.62 6 13.53V13.46C6 12.38 6.88 11.5 7.97 11.5Z\" undefined=\"1\"></path>\n<path stroke-linejoin=\"round\" stroke-linecap=\"round\" stroke-miterlimit=\"10\" stroke-width=\"2\" stroke=\"\" d=\"M17 8.5C15.23 8.97 14.07 10.84 14.01 13.27C14 13.33 14 13.4 14 13.47V13.5\"></path>\n<path stroke-linejoin=\"round\" stroke-linecap=\"round\" stroke-miterlimit=\"10\" stroke-width=\"2\" stroke=\"\" d=\"M9 8.5C7.23 8.97 6.07 10.84 6.01 13.27C6 13.33 6 13.4 6 13.47V13.5\"></path>\n<path stroke-linejoin=\"round\" stroke-linecap=\"round\" stroke-miterlimit=\"10\" stroke-width=\"2\" stroke=\"\" d=\"M15.97 11.5H16.04C17.12 11.5 18 12.38 18 13.47V13.53C18 14.62 17.12 15.5 16.03 15.5H15.96C14.88 15.5 14 14.62 14 13.53V13.46C14 12.38 14.88 11.5 15.97 11.5Z\"></path>\n<path stroke-linejoin=\"round\" stroke-linecap=\"round\" stroke-miterlimit=\"10\" stroke-width=\"2\" stroke=\"\" d=\"M7.97 11.5H8.04C9.12 11.5 10 12.38 10 13.47V13.53C10 14.62 9.12 15.5 8.03 15.5H7.97C6.88 15.5 6 14.62 6 13.53V13.46C6 12.38 6.88 11.5 7.97 11.5Z\"></path>\n</svg>\n</span><p> Mybatis 的映射文件中，前面我们的 SQL 都是比较简单的，有些时候业务逻辑复杂时，我们的 SQL是动 态变化的，此时在前面的学习中我们的 SQL 就不能满足要求了。</p></blockquote>\n","text":"动态sql语句**动态sql语句概述 ** Mybatis 的映射文件中，前面我们的 SQL 都是比较简单的，有些时候业务逻辑复杂时，我们的 SQL是动 态变化的，此时在前面的学习中我们的 SQL 就不能满足要求了。 ","link":"","photos":[],"count_time":{"symbolsCount":119,"symbolsTime":"1 mins."},"categories":[],"tags":[],"toc":"<ol class=\"toc\"><li class=\"toc-item toc-level-4\"><a class=\"toc-link\" href=\"#%E5%8A%A8%E6%80%81sql%E8%AF%AD%E5%8F%A5\"><span class=\"toc-text\">动态sql语句</span></a></li></ol>","author":{"name":"Aurora","slug":"blog-author","avatar":"https://img-blog.csdnimg.cn/20210313122054101.png","link":"/","description":"","socials":{"github":"","twitter":"","stackoverflow":"","wechat":"","qq":"","weibo":"","zhihu":"","csdn":"","juejin":"","customs":{}}},"mapped":true,"prev_post":{"title":"Spring基础了解","uid":"a519dcebcf7b75aa7909ffb897e4913c","slug":"Spring-base","date":"2021-05-02T06:22:41.000Z","updated":"2021-05-02T08:29:03.294Z","comments":true,"path":"api/articles/Spring-base.json","keywords":null,"cover":[],"text":"Spring 简介​ Spring 是分层的 full-stack（全栈） 轻量级开源框架，以IoC和 AOP 为内核，提供了展现层Spring MVC和业务层事务管理等众多的企业级应⽤技术，还能整合开源世界众多著名的第三⽅框架和类库，已 经成为使⽤最多的Java EE企业应⽤开...","link":"","photos":[],"count_time":{"symbolsCount":"2.6k","symbolsTime":"2 mins."},"categories":[],"tags":[],"author":{"name":"Aurora","slug":"blog-author","avatar":"https://img-blog.csdnimg.cn/20210313122054101.png","link":"/","description":"","socials":{"github":"","twitter":"","stackoverflow":"","wechat":"","qq":"","weibo":"","zhihu":"","csdn":"","juejin":"","customs":{}}}},"next_post":{"title":"alloc&init探究","uid":"20c5d0afd79142c4ce377e5e3d6eadea","slug":"alloc","date":"2021-05-01T09:45:39.000Z","updated":"2021-05-02T11:46:43.467Z","comments":true,"path":"api/articles/alloc.json","keywords":null,"cover":[],"text":"alloc 和 init 基本原理LGPerson *p &#x3D; [[LGPerson alloc] init]; LGPerson *p1 &#x3D; [p init]; &#x2F;&#x2F; objc_msgSend （id 消息接收者，sel 发送消息） LGP...","link":"","photos":[],"count_time":{"symbolsCount":"4.6k","symbolsTime":"4 mins."},"categories":[],"tags":[],"author":{"name":"Aurora","slug":"blog-author","avatar":"https://img-blog.csdnimg.cn/20210313122054101.png","link":"/","description":"","socials":{"github":"","twitter":"","stackoverflow":"","wechat":"","qq":"","weibo":"","zhihu":"","csdn":"","juejin":"","customs":{}}}}}